psp_scan/__init__.py
psp_scan/__main__.py
psp_scan/blocks.py
psp_scan/cli.py
psp_scan/files.py
psp_scan/image.py
psp_scan/layers.py
psp_scan/local_dev.py
psp_scan/masks.py
psp_scan/structs.py
psp_scan/utils.py
psp_scan-0.9.dist-info/DESCRIPTION.rst
psp_scan-0.9.dist-info/METADATA
psp_scan-0.9.dist-info/RECORD
psp_scan-0.9.dist-info/WHEEL
psp_scan-0.9.dist-info/metadata.json
psp_scan-0.9.dist-info/top_level.txt
