Metadata-Version: 2.0
Name: psp-scan
Version: 0.9
Summary: Python package for working with Paintshop Pro files
Home-page: https://github.com/Crawfishpress/psp_scan
Author: John Crawford
Author-email: psp_dev@crawfishpress.com
License: MIT License
Keywords: paintshoppro psp imaging conversion pil pillow
Platform: UNKNOWN
Classifier: Development Status :: 3 - Alpha
Classifier: Environment :: Console
Classifier: Intended Audience :: Developers
Classifier: Intended Audience :: End Users/Desktop
Classifier: License :: OSI Approved :: MIT License
Classifier: Operating System :: Microsoft
Classifier: Operating System :: Microsoft :: Windows
Classifier: Operating System :: Microsoft :: Windows :: Windows 7
Classifier: Programming Language :: Python
Classifier: Programming Language :: Python :: 2 :: Only
Classifier: Programming Language :: Python :: 2.7
Classifier: Topic :: Multimedia :: Graphics
Classifier: Topic :: Multimedia :: Graphics :: Graphics Conversion
Classifier: Topic :: Software Development :: Libraries :: Python Modules
Requires-Dist: Pillow (>=3.3.0)
